Workbook

Sheet Bets
A1: Jim "Mattress Mack" McIngvale — Publicly Reported Betting History
A2: Compiled from public reports (ESPN, Las Vegas Review-Journal, Houston Chronicle, CBS, sportsbook confirmations). Most bets hedge Gallery Furniture money-back promotions. Blank Wager/Payout cells = amount not publicly reported. Payout & Net are formulas.
A4: Date | B4: Sport | C4: Pick (Team / Side) | D4: Opponent | E4: Bet Type / Details | F4: Sportsbook | G4: Odds (American) | H4: Wager ($) | I4: Result | J4: Total Payout ($) | K4: Net Profit/Loss ($) | L4: Source
A5: 2019-10 | B5: MLB | C5: Houston Astros | D5: Washington Nationals | E5: Futures/series — 2019 World Series (multiple wagers, 3 states) | F5: Multiple books | H5: 13000000 | I5: Loss | J5: =IF(I5="Loss",0,IF(OR(H5="",G5=""),"",IF(G5>0,H5*(1+G5/100),H5*(1+100/ABS(G5))))) -> 0 | K5: =IF(H5="","",IF(I5="Loss",-H5,IF(J5="","",J5-H5))) -> -13000000 | L5: Houston Chronicle / LV Review-Journal
A6: 2020-02-02 | B6: NFL | C6: San Francisco 49ers | D6: Kansas City Chiefs | E6: Super Bowl LIV (tied to store promotion) | F6: Reported | H6: 1000000 | I6: Loss | J6: =IF(I6="Loss",0,IF(OR(H6="",G6=""),"",IF(G6>0,H6*(1+G6/100),H6*(1+100/ABS(G6))))) -> 0 | K6: =IF(H6="","",IF(I6="Loss",-H6,IF(J6="","",J6-H6))) -> -1000000 | L6: LegalSportsBetting
A7: 2021-02-07 | B7: NFL | C7: Tampa Bay Buccaneers +3.5 | D7: Kansas City Chiefs | E7: Spread — Super Bowl LV | F7: DraftKings | G7: -127 | H7: 3460000 | I7: Win | J7: =IF(I7="Loss",0,IF(OR(H7="",G7=""),"",IF(G7>0,H7*(1+G7/100),H7*(1+100/ABS(G7))))) -> 6184409.4 | K7: =IF(H7="","",IF(I7="Loss",-H7,IF(J7="","",J7-H7))) -> 2724409.4 | L7: ESPN / Action Network
A8: 2021-05-01 | B8: Horse racing | C8: Essential Quality | D8: Field | E8: 2021 Kentucky Derby winner | F8: Multiple books | H8: 4000000 | I8: Loss | J8: =IF(I8="Loss",0,IF(OR(H8="",G8=""),"",IF(G8>0,H8*(1+G8/100),H8*(1+100/ABS(G8))))) -> 0 | K8: =IF(H8="","",IF(I8="Loss",-H8,IF(J8="","",J8-H8))) -> -4000000 | L8: LegalSportsBetting
A9: 2021-10 | B9: MLB | C9: Houston Astros | D9: Atlanta Braves | E9: 2021 World Series | F9: Multiple books | H9: 3200000 | I9: Loss | J9: =IF(I9="Loss",0,IF(OR(H9="",G9=""),"",IF(G9>0,H9*(1+G9/100),H9*(1+100/ABS(G9))))) -> 0 | K9: =IF(H9="","",IF(I9="Loss",-H9,IF(J9="","",J9-H9))) -> -3200000 | L9: CBS News
A10: 2021-11 | B10: NFL | C10: Tennessee Titans | D10: Field | E10: Futures — Super Bowl LVI champion | F10: Reported | H10: 700000 | I10: Loss | J10: =IF(I10="Loss",0,IF(OR(H10="",G10=""),"",IF(G10>0,H10*(1+G10/100),H10*(1+100/ABS(G10))))) -> 0 | K10: =IF(H10="","",IF(I10="Loss",-H10,IF(J10="","",J10-H10))) -> -700000 | L10: LegalSportsBetting
A11: 2021-11 | B11: NFL | C11: New England Patriots | D11: Field | E11: Futures — Super Bowl LVI champion | F11: Reported | H11: 2000000 | I11: Loss | J11: =IF(I11="Loss",0,IF(OR(H11="",G11=""),"",IF(G11>0,H11*(1+G11/100),H11*(1+100/ABS(G11))))) -> 0 | K11: =IF(H11="","",IF(I11="Loss",-H11,IF(J11="","",J11-H11))) -> -2000000 | L11: LegalSportsBetting
A12: 2022-01-10 | B12: CFB | C12: Alabama | D12: Georgia | E12: CFP National Championship | F12: Multiple books | H12: 6200000 | I12: Loss | J12: =IF(I12="Loss",0,IF(OR(H12="",G12=""),"",IF(G12>0,H12*(1+G12/100),H12*(1+100/ABS(G12))))) -> 0 | K12: =IF(H12="","",IF(I12="Loss",-H12,IF(J12="","",J12-H12))) -> -6200000 | L12: LegalSportsBetting
A13: 2022-02-13 | B13: NFL | C13: Cincinnati Bengals | D13: Los Angeles Rams | E13: Moneyline — Super Bowl LVI ($4.53M Caesars + ~$5M pre-kickoff) | F13: Caesars + others | G13: 170 | H13: 9500000 | I13: Loss | J13: =IF(I13="Loss",0,IF(OR(H13="",G13=""),"",IF(G13>0,H13*(1+G13/100),H13*(1+100/ABS(G13))))) -> 0 | K13: =IF(H13="","",IF(I13="Loss",-H13,IF(J13="","",J13-H13))) -> -9500000 | L13: OnlineBookiesOffers / LegalSportsBetting
A14: 2022-04-04 | B14: NCAAB | C14: Kansas | D14: North Carolina | E14: NCAA championship (futures + title game) | F14: Multiple books | H14: 8800000 | I14: Win | J14: 21000000 | K14: =IF(H14="","",IF(I14="Loss",-H14,IF(J14="","",J14-H14))) -> 12200000 | L14: Houston Chronicle / LV Review-Journal
A15: 2022-05-07 | B15: Horse racing | C15: Epicenter | D15: Field | E15: 2022 Kentucky Derby winner | F15: Multiple books | H15: 2600000 | I15: Loss | J15: =IF(I15="Loss",0,IF(OR(H15="",G15=""),"",IF(G15>0,H15*(1+G15/100),H15*(1+100/ABS(G15))))) -> 0 | K15: =IF(H15="","",IF(I15="Loss",-H15,IF(J15="","",J15-H15))) -> -2600000 | L15: LV Review-Journal
A16: 2022-05 | B16: MLB | C16: Houston Astros | D16: Philadelphia Phillies | E16: Futures — 2022 World Series ($3M Caesars +1000, $2M Barstool, $2M BetMGM, $1M WynnBET + more) | F16: 5 sportsbooks | H16: 10000000 | I16: Win | J16: 82600000 | K16: =IF(H16="","",IF(I16="Loss",-H16,IF(J16="","",J16-H16))) -> 72600000 | L16: LV Review-Journal / ESPN / CBS
A17: 2023-01-09 | B17: CFB | C17: TCU | D17: Georgia | E17: CFP National Championship | F17: Reported | H17: 3000000 | I17: Loss | J17: =IF(I17="Loss",0,IF(OR(H17="",G17=""),"",IF(G17>0,H17*(1+G17/100),H17*(1+100/ABS(G17))))) -> 0 | K17: =IF(H17="","",IF(I17="Loss",-H17,IF(J17="","",J17-H17))) -> -3000000 | L17: Chron.com
A18: 2023-01-22 | B18: NFL | C18: Dallas Cowboys | D18: San Francisco 49ers | E18: Divisional playoff | F18: Reported | H18: 2000000 | I18: Loss | J18: =IF(I18="Loss",0,IF(OR(H18="",G18=""),"",IF(G18>0,H18*(1+G18/100),H18*(1+100/ABS(G18))))) -> 0 | K18: =IF(H18="","",IF(I18="Loss",-H18,IF(J18="","",J18-H18))) -> -2000000 | L18: Chron.com
A19: 2023-03 | B19: NCAAB | C19: Houston Cougars | D19: Field | E19: Futures — NCAA champion (lost in Sweet 16) | F19: Reported | H19: 4000000 | I19: Loss | J19: =IF(I19="Loss",0,IF(OR(H19="",G19=""),"",IF(G19>0,H19*(1+G19/100),H19*(1+100/ABS(G19))))) -> 0 | K19: =IF(H19="","",IF(I19="Loss",-H19,IF(J19="","",J19-H19))) -> -4000000 | L19: Chron.com (Houston Chronicle reports $2.5M)
A20: 2023-05-06 | B20: Horse racing | C20: 2023 Kentucky Derby wagers | D20: Field | E20: Derby wagers (horse not specified in reports) | F20: Reported | H20: 1200000 | I20: Loss | J20: =IF(I20="Loss",0,IF(OR(H20="",G20=""),"",IF(G20>0,H20*(1+G20/100),H20*(1+100/ABS(G20))))) -> 0 | K20: =IF(H20="","",IF(I20="Loss",-H20,IF(J20="","",J20-H20))) -> -1200000 | L20: Houston Chronicle
A21: 2023-03/09 | B21: MLB | C21: Houston Astros | D21: Texas Rangers (ALCS exit) | E21: Futures — 2023 World Series ($1.9M in March + $2M at +600 in Sept; ~$8M total reported) | F21: DraftKings + others | G21: 600 | H21: 8000000 | I21: Loss | J21: =IF(I21="Loss",0,IF(OR(H21="",G21=""),"",IF(G21>0,H21*(1+G21/100),H21*(1+100/ABS(G21))))) -> 0 | K21: =IF(H21="","",IF(I21="Loss",-H21,IF(J21="","",J21-H21))) -> -8000000 | L21: Houston Chronicle / Chron.com / SI
A22: 2024-01-20 | B22: NFL | C22: Houston Texans | D22: Baltimore Ravens | E22: Divisional playoff | F22: Reported | H22: 300000 | I22: Loss | J22: =IF(I22="Loss",0,IF(OR(H22="",G22=""),"",IF(G22>0,H22*(1+G22/100),H22*(1+100/ABS(G22))))) -> 0 | K22: =IF(H22="","",IF(I22="Loss",-H22,IF(J22="","",J22-H22))) -> -300000 | L22: Houston Chronicle
A23: 2024-03 | B23: NCAAB | C23: Houston Cougars | D23: Field | E23: Futures — NCAA champion (lost in Sweet 16) | F23: Reported | I23: Loss | J23: =IF(I23="Loss",0,IF(OR(H23="",G23=""),"",IF(G23>0,H23*(1+G23/100),H23*(1+100/ABS(G23))))) -> 0 | K23: =IF(H23="","",IF(I23="Loss",-H23,IF(J23="","",J23-H23))) | L23: CW39 / AP
A24: 2026-01-29 | B24: NFL | C24: New England Patriots | D24: Seattle Seahawks | E24: Super Bowl LX ($2M Caesars — largest reported SB bet — plus additional wagers; ~$3.3M total) | F24: Caesars + others | H24: 3300000 | I24: Loss | J24: =IF(I24="Loss",0,IF(OR(H24="",G24=""),"",IF(G24>0,H24*(1+G24/100),H24*(1+100/ABS(G24))))) -> 0 | K24: =IF(H24="","",IF(I24="Loss",-H24,IF(J24="","",J24-H24))) -> -3300000 | L24: Houston Chronicle / ESPN / CW39
A26: Notes & assumptions:
A27: • Pick = the team/horse/side McIngvale backed; Opponent = who they played ("Field" for futures and race winners).
A28: • Blue payout cells are hardcoded from reported figures: Kansas 2022 = $12.2M profit (LV Review-Journal); Astros 2022 = $72.6M in winnings per LVRJ (other outlets report a ~$75M total payout).
A29: • Most wagers were placed as hedges against Gallery Furniture money-back promotions, so a lost bet is typically offset by retained store revenue (and vice versa).
A30: • Feb 2014 Super Bowl XLVIII: his unhedged Seahawks promotion cost ~$13M in customer refunds — a promotion loss, not a sportsbook bet, so it is excluded from the table.
A31: • He reportedly skipped betting Super Bowl LIX (2025) while recovering from open-heart surgery.
A32: • Conflicting figures noted in-row: Houston 2023 NCAA reported as $4M (Chron.com) or $2.5M (Houston Chronicle); Astros 2023 total reported as "nearly $8M"; Super Bowl LX total ~$3.3M (CW39).
A33: • Many wagers were split across several sportsbooks; odds shown only where a single reported price applies. Payout formula (where used): positive odds = Wager × (1 + Odds/100); negative = Wager × (1 + 100/|Odds|).
A34: • Sources: ESPN; Las Vegas Review-Journal; Houston Chronicle / Chron.com; CBS News; Action Network; LegalSportsBetting.com; OnlineBookiesOffers.co.uk; CW39.

Sheet Summary
A1: Summary — Publicly Reported Bets
A3: Total bets tracked | B3: =COUNTA(Bets!I5:I24) -> 20
A4: Wins | B4: =COUNTIF(Bets!I5:I24,"Win") -> 3
A5: Losses | B5: =COUNTIF(Bets!I5:I24,"Loss") -> 17
A6: Win rate | B6: =IF(B3=0,0,B4/B3) -> 0.15
A7: Bets with reported stake | B7: =COUNT(Bets!H5:H24) -> 19
A8: Total wagered (reported stakes) | B8: =SUM(Bets!H5:H24) -> 86260000
A9: Total payouts received | B9: =SUM(Bets!J5:J24) -> 1.0978441e+08
A10: Net profit / loss | B10: =SUM(Bets!K5:K24) -> 23524409
A11: ROI on reported stakes | B11: =IF(B8=0,0,B10/B8) -> 0.27271516
A12: Biggest single win (net) | B12: =MAX(Bets!K5:K24) -> 72600000
A13: Biggest single loss (net) | B13: =MIN(Bets!K5:K24) -> -13000000
A14: Largest wager | B14: =MAX(Bets!H5:H24) -> 13000000
A17: By Sport
A18: Sport | B18: Bets | C18: Wins | D18: Losses | E18: Wagered ($) | F18: Net ($)
A19: CFB | B19: =COUNTIF(Bets!$B$5:$B$24,A19) -> 2 | C19: =COUNTIFS(Bets!$B$5:$B$24,A19,Bets!$I$5:$I$24,"Win") -> 0 | D19: =COUNTIFS(Bets!$B$5:$B$24,A19,Bets!$I$5:$I$24,"Loss") -> 2 | E19: =SUMIF(Bets!$B$5:$B$24,A19,Bets!$H$5:$H$24) -> 9200000 | F19: =SUMIF(Bets!$B$5:$B$24,A19,Bets!$K$5:$K$24) -> -9200000
A20: Horse racing | B20: =COUNTIF(Bets!$B$5:$B$24,A20) -> 3 | C20: =COUNTIFS(Bets!$B$5:$B$24,A20,Bets!$I$5:$I$24,"Win") -> 0 | D20: =COUNTIFS(Bets!$B$5:$B$24,A20,Bets!$I$5:$I$24,"Loss") -> 3 | E20: =SUMIF(Bets!$B$5:$B$24,A20,Bets!$H$5:$H$24) -> 7800000 | F20: =SUMIF(Bets!$B$5:$B$24,A20,Bets!$K$5:$K$24) -> -7800000
A21: MLB | B21: =COUNTIF(Bets!$B$5:$B$24,A21) -> 4 | C21: =COUNTIFS(Bets!$B$5:$B$24,A21,Bets!$I$5:$I$24,"Win") -> 1 | D21: =COUNTIFS(Bets!$B$5:$B$24,A21,Bets!$I$5:$I$24,"Loss") -> 3 | E21: =SUMIF(Bets!$B$5:$B$24,A21,Bets!$H$5:$H$24) -> 34200000 | F21: =SUMIF(Bets!$B$5:$B$24,A21,Bets!$K$5:$K$24) -> 48400000
A22: NCAAB | B22: =COUNTIF(Bets!$B$5:$B$24,A22) -> 3 | C22: =COUNTIFS(Bets!$B$5:$B$24,A22,Bets!$I$5:$I$24,"Win") -> 1 | D22: =COUNTIFS(Bets!$B$5:$B$24,A22,Bets!$I$5:$I$24,"Loss") -> 2 | E22: =SUMIF(Bets!$B$5:$B$24,A22,Bets!$H$5:$H$24) -> 12800000 | F22: =SUMIF(Bets!$B$5:$B$24,A22,Bets!$K$5:$K$24) -> 8200000
A23: NFL | B23: =COUNTIF(Bets!$B$5:$B$24,A23) -> 8 | C23: =COUNTIFS(Bets!$B$5:$B$24,A23,Bets!$I$5:$I$24,"Win") -> 1 | D23: =COUNTIFS(Bets!$B$5:$B$24,A23,Bets!$I$5:$I$24,"Loss") -> 7 | E23: =SUMIF(Bets!$B$5:$B$24,A23,Bets!$H$5:$H$24) -> 22260000 | F23: =SUMIF(Bets!$B$5:$B$24,A23,Bets!$K$5:$K$24) -> -16075591
A24: Total | B24: =SUM(B19:B23) -> 20 | C24: =SUM(C19:C23) -> 3 | D24: =SUM(D19:D23) -> 17 | E24: =SUM(E19:E23) -> 86260000 | F24: =SUM(F19:F23) -> 23524409
A26: Dollar totals only include bets with a publicly reported stake. Win/loss counts include every tracked bet.
